{
  "generatedAt": "2026-07-09 18:04:11",
  "latestFeatureDate": "2026-07-09",
  "featureRowCount": 31,
  "labeledFeatureRowCount": 0,
  "paperOutcomeCount": 60,
  "paperHitRate": 31.67,
  "paperStrongHitRate": 11.67,
  "paperAverageReturnPercent": -0.96,
  "targets": {
    "dailyHitRate": 75.0,
    "dailyAverageReturnPercent": 8.0,
    "weeklyHitRate": 75.0,
    "weeklyAverageReturnPercent": 8.0
  },
  "nextStep": "Accumulate labeled 14:30 paper outcomes before enabling ranker model promotion."
}
